[{"_id":{"$oid":"59351e15c3b3736ee0fa5f60"},"_class":"it.euris.fullstack.model.Person","name":"Mario","surname":"Bianchi","dateOfBirth":{"$date":"1985-11-22T23:00:00.000Z"},"placeOfBirth":"Messina","address":"Via Indipendenza 1","city":"Bologna","phoneNumber":"0511111111","gender":"MALE"},{"_id":{"$oid":"59351e15c3b3736ee0fa5f61"},"_class":"it.euris.fullstack.model.Person","name":"Luca","surname":"Bianchi","dateOfBirth":{"$date":"1985-11-22T23:00:00.000Z"},"placeOfBirth":"Messina","address":"Via Indipendenza 1","city":"Roma","phoneNumber":"0511111111","gender":"FEMALE"},{"_id":{"$oid":"59351e15c3b3736ee0fa5f62"},"_class":"it.euris.fullstack.model.Person","name":"Luca","surname":"Bianchi","dateOfBirth":{"$date":"1985-11-22T23:00:00.000Z"},"placeOfBirth":"Messina","address":"Via Indipendenza 1","city":"Roma","phoneNumber":"0511111111","gender":"MALE"},{"_id":{"$oid":"59351e15c3b3736ee0fa5f63"},"_class":"it.euris.fullstack.model.Person","name":"Mario","surname":"Bianchi","dateOfBirth":{"$date":"1985-11-22T23:00:00.000Z"},"placeOfBirth":"Messina","address":"Via Indipendenza 1","city":"Bologna","phoneNumber":"0511111111","gender":"MALE"},{"_id":{"$oid":"59351e15c3b3736ee0fa5f64"},"_class":"it.euris.fullstack.model.Person","name":"Luca","surname":"Bianchi","dateOfBirth":{"$date":"1985-11-22T23:00:00.000Z"},"placeOfBirth":"Messina","address":"Via Indipendenza 1","city":"Roma","phoneNumber":"0511111111","gender":"MALE"},{"_id":{"$oid":"59351e15c3b3736ee0fa5f65"},"_class":"it.euris.fullstack.model.Person","name":"Luca","surname":"Bianchi","dateOfBirth":{"$date":"1985-11-22T23:00:00.000Z"},"placeOfBirth":"Messina","address":"Via Indipendenza 1","city":"Bologna","phoneNumber":"0511111111","gender":"MALE"},{"_id":{"$oid":"59351e15c3b3736ee0fa5f66"},"_class":"it.euris.fullstack.model.Person","name":"Luca","surname":"Bianchi","dateOfBirth":{"$date":"1985-11-22T23:00:00.000Z"},"placeOfBirth":"Messina","address":"Via Indipendenza 1","city":"Roma","phoneNumber":"0511111111","gender":"FEMALE"},{"_id":{"$oid":"59351e15c3b3736ee0fa5f67"},"_class":"it.euris.fullstack.model.Person","name":"Luca","surname":"Bianchi","dateOfBirth":{"$date":"1985-11-22T23:00:00.000Z"},"placeOfBirth":"Messina","address":"Via Indipendenza 1","city":"Roma","phoneNumber":"0511111111","gender":"MALE"},{"_id":{"$oid":"59351e15c3b3736ee0fa5f68"},"_class":"it.euris.fullstack.model.Person","name":"Luca","surname":"Bianchi","dateOfBirth":{"$date":"1985-11-22T23:00:00.000Z"},"placeOfBirth":"Messina","address":"Via Indipendenza 1","city":"Bologna","phoneNumber":"0511111111","gender":"MALE"},{"_id":{"$oid":"59351e15c3b3736ee0fa5f69"},"_class":"it.euris.fullstack.model.Person","name":"Luca","surname":"Rossi","dateOfBirth":{"$date":"1985-11-22T23:00:00.000Z"},"placeOfBirth":"Messina","address":"Via Indipendenza 1","city":"Roma","phoneNumber":"0511111111","gender":"MALE"},{"_id":{"$oid":"59351e15c3b3736ee0fa5f6a"},"_class":"it.euris.fullstack.model.Person","name":"Luca","surname":"Bianchi","dateOfBirth":{"$date":"1985-11-22T23:00:00.000Z"},"placeOfBirth":"Messina","address":"Via Indipendenza 1","city":"Roma","phoneNumber":"0511111111","gender":"FEMALE"},{"_id":{"$oid":"59351e15c3b3736ee0fa5f6b"},"_class":"it.euris.fullstack.model.Person","name":"Mario","surname":"Bianchi","dateOfBirth":{"$date":"1985-11-22T23:00:00.000Z"},"placeOfBirth":"Messina","address":"Via Indipendenza 1","city":"Bologna","phoneNumber":"0511111111","gender":"MALE"},{"_id":{"$oid":"59351e15c3b3736ee0fa5f6c"},"_class":"it.euris.fullstack.model.Person","name":"Mario","surname":"Bianchi","dateOfBirth":{"$date":"1985-11-22T23:00:00.000Z"},"placeOfBirth":"Messina","address":"Via Indipendenza 1","city":"Roma","phoneNumber":"0511111111","gender":"MALE"},{"_id":{"$oid":"59351e15c3b3736ee0fa5f6d"},"_class":"it.euris.fullstack.model.Person","name":"Luca","surname":"Bianchi","dateOfBirth":{"$date":"1985-11-22T23:00:00.000Z"},"placeOfBirth":"Messina","address":"Via Indipendenza 1","city":"Roma","phoneNumber":"0511111111","gender":"FEMALE"},{"_id":{"$oid":"59351e15c3b3736ee0fa5f6e"},"_class":"it.euris.fullstack.model.Person","name":"Luca","surname":"Rossi","dateOfBirth":{"$date":"1985-11-22T23:00:00.000Z"},"placeOfBirth":"Messina","address":"Via Indipendenza 1","city":"Bologna","phoneNumber":"0511111111","gender":"MALE"},{"_id":{"$oid":"59351e15c3b3736ee0fa5f6f"},"_class":"it.euris.fullstack.model.Person","name":"Luca","surname":"Bianchi","dateOfBirth":{"$date":"1985-11-22T23:00:00.000Z"},"placeOfBirth":"Messina","address":"Via Indipendenza 1","city":"Bologna","phoneNumber":"0511111111","gender":"MALE"},{"_id":{"$oid":"59351e15c3b3736ee0fa5f70"},"_class":"it.euris.fullstack.model.Person","name":"Mario","surname":"Bianchi","dateOfBirth":{"$date":"1985-11-22T23:00:00.000Z"},"placeOfBirth":"Messina","address":"Via Indipendenza 1","city":"Roma","phoneNumber":"0511111111","gender":"FEMALE"},{"_id":{"$oid":"59351e15c3b3736ee0fa5f71"},"_class":"it.euris.fullstack.model.Person","name":"Mario","surname":"Bianchi","dateOfBirth":{"$date":"1985-11-22T23:00:00.000Z"},"placeOfBirth":"Messina","address":"Via Indipendenza 1","city":"Bologna","phoneNumber":"0511111111","gender":"FEMALE"},{"_id":{"$oid":"59351e15c3b3736ee0fa5f72"},"_class":"it.euris.fullstack.model.Person","name":"Luca","surname":"Bianchi","dateOfBirth":{"$date":"1985-11-22T23:00:00.000Z"},"placeOfBirth":"Messina","address":"Via Indipendenza 1","city":"Bologna","phoneNumber":"0511111111","gender":"FEMALE"},{"_id":{"$oid":"59351e15c3b3736ee0fa5f73"},"_class":"it.euris.fullstack.model.Person","name":"Luca","surname":"Bianchi","dateOfBirth":{"$date":"1985-11-22T23:00:00.000Z"},"placeOfBirth":"Messina","address":"Via Indipendenza 1","city":"Bologna","phoneNumber":"0511111111","gender":"MALE"},{"_id":{"$oid":"59351e15c3b3736ee0fa5f74"},"_class":"it.euris.fullstack.model.Person","name":"Luca","surname":"Bianchi","dateOfBirth":{"$date":"1985-11-22T23:00:00.000Z"},"placeOfBirth":"Messina","address":"Via Indipendenza 1","city":"Bologna","phoneNumber":"0511111111","gender":"FEMALE"},{"_id":{"$oid":"59351e15c3b3736ee0fa5f75"},"_class":"it.euris.fullstack.model.Person","name":"Luca","surname":"Rossi","dateOfBirth":{"$date":"1985-11-22T23:00:00.000Z"},"placeOfBirth":"Messina","address":"Via Indipendenza 1","city":"Roma","phoneNumber":"0511111111","gender":"FEMALE"},{"_id":{"$oid":"59351e15c3b3736ee0fa5f76"},"_class":"it.euris.fullstack.model.Person","name":"Luca","surname":"Bianchi","dateOfBirth":{"$date":"1985-11-22T23:00:00.000Z"},"placeOfBirth":"Messina","address":"Via Indipendenza 1","city":"Roma","phoneNumber":"0511111111","gender":"MALE"},{"_id":{"$oid":"59351e15c3b3736ee0fa5f77"},"_class":"it.euris.fullstack.model.Person","name":"Mario","surname":"Rossi","dateOfBirth":{"$date":"1985-11-22T23:00:00.000Z"},"placeOfBirth":"Messina","address":"Via Indipendenza 1","city":"Bologna","phoneNumber":"0511111111","gender":"MALE"},{"_id":{"$oid":"59351e15c3b3736ee0fa5f78"},"_class":"it.euris.fullstack.model.Person","name":"Mario","surname":"Bianchi","dateOfBirth":{"$date":"1985-11-22T23:00:00.000Z"},"placeOfBirth":"Messina","address":"Via Indipendenza 1","city":"Bologna","phoneNumber":"0511111111","gender":"FEMALE"},{"_id":{"$oid":"59351e15c3b3736ee0fa5f79"},"_class":"it.euris.fullstack.model.Person","name":"Mario","surname":"Rossi","dateOfBirth":{"$date":"1985-11-22T23:00:00.000Z"},"placeOfBirth":"Messina","address":"Via Indipendenza 1","city":"Roma","phoneNumber":"0511111111","gender":"FEMALE"},{"_id":{"$oid":"59351e15c3b3736ee0fa5f7a"},"_class":"it.euris.fullstack.model.Person","name":"Luca","surname":"Rossi","dateOfBirth":{"$date":"1985-11-22T23:00:00.000Z"},"placeOfBirth":"Messina","address":"Via Indipendenza 1","city":"Bologna","phoneNumber":"0511111111","gender":"FEMALE"},{"_id":{"$oid":"59351e15c3b3736ee0fa5f7b"},"_class":"it.euris.fullstack.model.Person","name":"Luca","surname":"Rossi","dateOfBirth":{"$date":"1985-11-22T23:00:00.000Z"},"placeOfBirth":"Messina","address":"Via Indipendenza 1","city":"Bologna","phoneNumber":"0511111111","gender":"MALE"},{"_id":{"$oid":"59351e15c3b3736ee0fa5f7c"},"_class":"it.euris.fullstack.model.Person","name":"Mario","surname":"Bianchi","dateOfBirth":{"$date":"1985-11-22T23:00:00.000Z"},"placeOfBirth":"Messina","address":"Via Indipendenza 1","city":"Bologna","phoneNumber":"0511111111","gender":"FEMALE"},{"_id":{"$oid":"59351e15c3b3736ee0fa5f7d"},"_class":"it.euris.fullstack.model.Person","name":"Mario","surname":"Rossi","dateOfBirth":{"$date":"1985-11-22T23:00:00.000Z"},"placeOfBirth":"Messina","address":"Via Indipendenza 1","city":"Roma","phoneNumber":"0511111111","gender":"FEMALE"},{"_id":{"$oid":"59351e15c3b3736ee0fa5f7e"},"_class":"it.euris.fullstack.model.Person","name":"Mario","surname":"Bianchi","dateOfBirth":{"$date":"1985-11-22T23:00:00.000Z"},"placeOfBirth":"Messina","address":"Via Indipendenza 1","city":"Bologna","phoneNumber":"0511111111","gender":"FEMALE"},{"_id":{"$oid":"59351e15c3b3736ee0fa5f7f"},"_class":"it.euris.fullstack.model.Person","name":"Mario","surname":"Bianchi","dateOfBirth":{"$date":"1985-11-22T23:00:00.000Z"},"placeOfBirth":"Messina","address":"Via Indipendenza 1","city":"Bologna","phoneNumber":"0511111111","gender":"MALE"},{"_id":{"$oid":"59351e15c3b3736ee0fa5f80"},"_class":"it.euris.fullstack.model.Person","name":"Mario","surname":"Rossi","dateOfBirth":{"$date":"1985-11-22T23:00:00.000Z"},"placeOfBirth":"Messina","address":"Via Indipendenza 1","city":"Bologna","phoneNumber":"0511111111","gender":"MALE"},{"_id":{"$oid":"59351e15c3b3736ee0fa5f81"},"_class":"it.euris.fullstack.model.Person","name":"Luca","surname":"Bianchi","dateOfBirth":{"$date":"1985-11-22T23:00:00.000Z"},"placeOfBirth":"Messina","address":"Via Indipendenza 1","city":"Bologna","phoneNumber":"0511111111","gender":"FEMALE"},{"_id":{"$oid":"59351e15c3b3736ee0fa5f82"},"_class":"it.euris.fullstack.model.Person","name":"Mario","surname":"Bianchi","dateOfBirth":{"$date":"1985-11-22T23:00:00.000Z"},"placeOfBirth":"Messina","address":"Via Indipendenza 1","city":"Roma","phoneNumber":"0511111111","gender":"MALE"},{"_id":{"$oid":"59351e15c3b3736ee0fa5f83"},"_class":"it.euris.fullstack.model.Person","name":"Mario","surname":"Rossi","dateOfBirth":{"$date":"1985-11-22T23:00:00.000Z"},"placeOfBirth":"Messina","address":"Via Indipendenza 1","city":"Bologna","phoneNumber":"0511111111","gender":"MALE"},{"_id":{"$oid":"59351e15c3b3736ee0fa5f84"},"_class":"it.euris.fullstack.model.Person","name":"Mario","surname":"Bianchi","dateOfBirth":{"$date":"1985-11-22T23:00:00.000Z"},"placeOfBirth":"Messina","address":"Via Indipendenza 1","city":"Bologna","phoneNumber":"0511111111","gender":"MALE"},{"_id":{"$oid":"59351e15c3b3736ee0fa5f85"},"_class":"it.euris.fullstack.model.Person","name":"Mario","surname":"Bianchi","dateOfBirth":{"$date":"1985-11-22T23:00:00.000Z"},"placeOfBirth":"Messina","address":"Via Indipendenza 1","city":"Bologna","phoneNumber":"0511111111","gender":"MALE"},{"_id":{"$oid":"59351e15c3b3736ee0fa5f86"},"_class":"it.euris.fullstack.model.Person","name":"Mario","surname":"Rossi","dateOfBirth":{"$date":"1985-11-22T23:00:00.000Z"},"placeOfBirth":"Messina","address":"Via Indipendenza 1","city":"Bologna","phoneNumber":"0511111111","gender":"MALE"},{"_id":{"$oid":"59351e15c3b3736ee0fa5f87"},"_class":"it.euris.fullstack.model.Person","name":"Luca","surname":"Rossi","dateOfBirth":{"$date":"1985-11-22T23:00:00.000Z"},"placeOfBirth":"Messina","address":"Via Indipendenza 1","city":"Bologna","phoneNumber":"0511111111","gender":"MALE"},{"_id":{"$oid":"59351e15c3b3736ee0fa5f88"},"_class":"it.euris.fullstack.model.Person","name":"Mario","surname":"Bianchi","dateOfBirth":{"$date":"1985-11-22T23:00:00.000Z"},"placeOfBirth":"Messina","address":"Via Indipendenza 1","city":"Roma","phoneNumber":"0511111111","gender":"FEMALE"},{"_id":{"$oid":"59351e15c3b3736ee0fa5f89"},"_class":"it.euris.fullstack.model.Person","name":"Luca","surname":"Bianchi","dateOfBirth":{"$date":"1985-11-22T23:00:00.000Z"},"placeOfBirth":"Messina","address":"Via Indipendenza 1","city":"Roma","phoneNumber":"0511111111","gender":"MALE"},{"_id":{"$oid":"59351e15c3b3736ee0fa5f8a"},"_class":"it.euris.fullstack.model.Person","name":"Luca","surname":"Rossi","dateOfBirth":{"$date":"1985-11-22T23:00:00.000Z"},"placeOfBirth":"Messina","address":"Via Indipendenza 1","city":"Bologna","phoneNumber":"0511111111","gender":"FEMALE"},{"_id":{"$oid":"59351e15c3b3736ee0fa5f8b"},"_class":"it.euris.fullstack.model.Person","name":"Mario","surname":"Rossi","dateOfBirth":{"$date":"1985-11-22T23:00:00.000Z"},"placeOfBirth":"Messina","address":"Via Indipendenza 1","city":"Bologna","phoneNumber":"0511111111","gender":"MALE"},{"_id":{"$oid":"59351e15c3b3736ee0fa5f8c"},"_class":"it.euris.fullstack.model.Person","name":"Mario","surname":"Rossi","dateOfBirth":{"$date":"1985-11-22T23:00:00.000Z"},"placeOfBirth":"Messina","address":"Via Indipendenza 1","city":"Bologna","phoneNumber":"0511111111","gender":"MALE"},{"_id":{"$oid":"59351e15c3b3736ee0fa5f8d"},"_class":"it.euris.fullstack.model.Person","name":"Luca","surname":"Bianchi","dateOfBirth":{"$date":"1985-11-22T23:00:00.000Z"},"placeOfBirth":"Messina","address":"Via Indipendenza 1","city":"Roma","phoneNumber":"0511111111","gender":"MALE"},{"_id":{"$oid":"59351e15c3b3736ee0fa5f8e"},"_class":"it.euris.fullstack.model.Person","name":"Mario","surname":"Rossi","dateOfBirth":{"$date":"1985-11-22T23:00:00.000Z"},"placeOfBirth":"Messina","address":"Via Indipendenza 1","city":"Roma","phoneNumber":"0511111111","gender":"FEMALE"},{"_id":{"$oid":"59351e15c3b3736ee0fa5f8f"},"_class":"it.euris.fullstack.model.Person","name":"Mario","surname":"Bianchi","dateOfBirth":{"$date":"1985-11-22T23:00:00.000Z"},"placeOfBirth":"Messina","address":"Via Indipendenza 1","city":"Roma","phoneNumber":"0511111111","gender":"FEMALE"},{"_id":{"$oid":"59351e15c3b3736ee0fa5f90"},"_class":"it.euris.fullstack.model.Person","name":"Mario","surname":"Bianchi","dateOfBirth":{"$date":"1985-11-22T23:00:00.000Z"},"placeOfBirth":"Messina","address":"Via Indipendenza 1","city":"Roma","phoneNumber":"0511111111","gender":"FEMALE"},{"_id":{"$oid":"59351e15c3b3736ee0fa5f91"},"_class":"it.euris.fullstack.model.Person","name":"Mario","surname":"Bianchi","dateOfBirth":{"$date":"1985-11-22T23:00:00.000Z"},"placeOfBirth":"Messina","address":"Via Indipendenza 1","city":"Bologna","phoneNumber":"0511111111","gender":"FEMALE"},{"_id":{"$oid":"59351e15c3b3736ee0fa5f92"},"_class":"it.euris.fullstack.model.Person","name":"Luca","surname":"Bianchi","dateOfBirth":{"$date":"1985-11-22T23:00:00.000Z"},"placeOfBirth":"Messina","address":"Via Indipendenza 1","city":"Roma","phoneNumber":"0511111111","gender":"FEMALE"},{"_id":{"$oid":"59351e15c3b3736ee0fa5f93"},"_class":"it.euris.fullstack.model.Person","name":"Mario","surname":"Bianchi","dateOfBirth":{"$date":"1985-11-22T23:00:00.000Z"},"placeOfBirth":"Messina","address":"Via Indipendenza 1","city":"Bologna","phoneNumber":"0511111111","gender":"MALE"},{"_id":{"$oid":"59351e15c3b3736ee0fa5f94"},"_class":"it.euris.fullstack.model.Person","name":"Luca","surname":"Rossi","dateOfBirth":{"$date":"1985-11-22T23:00:00.000Z"},"placeOfBirth":"Messina","address":"Via Indipendenza 1","city":"Bologna","phoneNumber":"0511111111","gender":"FEMALE"},{"_id":{"$oid":"59351e15c3b3736ee0fa5f95"},"_class":"it.euris.fullstack.model.Person","name":"Luca","surname":"Rossi","dateOfBirth":{"$date":"1985-11-22T23:00:00.000Z"},"placeOfBirth":"Messina","address":"Via Indipendenza 1","city":"Roma","phoneNumber":"0511111111","gender":"FEMALE"},{"_id":{"$oid":"59351e15c3b3736ee0fa5f96"},"_class":"it.euris.fullstack.model.Person","name":"Mario","surname":"Rossi","dateOfBirth":{"$date":"1985-11-22T23:00:00.000Z"},"placeOfBirth":"Messina","address":"Via Indipendenza 1","city":"Roma","phoneNumber":"0511111111","gender":"MALE"},{"_id":{"$oid":"59351e15c3b3736ee0fa5f97"},"_class":"it.euris.fullstack.model.Person","name":"Mario","surname":"Bianchi","dateOfBirth":{"$date":"1985-11-22T23:00:00.000Z"},"placeOfBirth":"Messina","address":"Via Indipendenza 1","city":"Roma","phoneNumber":"0511111111","gender":"FEMALE"},{"_id":{"$oid":"59351e15c3b3736ee0fa5f98"},"_class":"it.euris.fullstack.model.Person","name":"Mario","surname":"Rossi","dateOfBirth":{"$date":"1985-11-22T23:00:00.000Z"},"placeOfBirth":"Messina","address":"Via Indipendenza 1","city":"Roma","phoneNumber":"0511111111","gender":"FEMALE"},{"_id":{"$oid":"59351e15c3b3736ee0fa5f99"},"_class":"it.euris.fullstack.model.Person","name":"Luca","surname":"Bianchi","dateOfBirth":{"$date":"1985-11-22T23:00:00.000Z"},"placeOfBirth":"Messina","address":"Via Indipendenza 1","city":"Bologna","phoneNumber":"0511111111","gender":"FEMALE"},{"_id":{"$oid":"59351e15c3b3736ee0fa5f9a"},"_class":"it.euris.fullstack.model.Person","name":"Mario","surname":"Rossi","dateOfBirth":{"$date":"1985-11-22T23:00:00.000Z"},"placeOfBirth":"Messina","address":"Via Indipendenza 1","city":"Bologna","phoneNumber":"0511111111","gender":"MALE"},{"_id":{"$oid":"59351e15c3b3736ee0fa5f9b"},"_class":"it.euris.fullstack.model.Person","name":"Mario","surname":"Bianchi","dateOfBirth":{"$date":"1985-11-22T23:00:00.000Z"},"placeOfBirth":"Messina","address":"Via Indipendenza 1","city":"Bologna","phoneNumber":"0511111111","gender":"MALE"},{"_id":{"$oid":"59351e15c3b3736ee0fa5f9c"},"_class":"it.euris.fullstack.model.Person","name":"Luca","surname":"Rossi","dateOfBirth":{"$date":"1985-11-22T23:00:00.000Z"},"placeOfBirth":"Messina","address":"Via Indipendenza 1","city":"Bologna","phoneNumber":"0511111111","gender":"MALE"},{"_id":{"$oid":"59351e15c3b3736ee0fa5f9d"},"_class":"it.euris.fullstack.model.Person","name":"Mario","surname":"Bianchi","dateOfBirth":{"$date":"1985-11-22T23:00:00.000Z"},"placeOfBirth":"Messina","address":"Via Indipendenza 1","city":"Roma","phoneNumber":"0511111111","gender":"MALE"},{"_id":{"$oid":"59351e15c3b3736ee0fa5f9e"},"_class":"it.euris.fullstack.model.Person","name":"Luca","surname":"Rossi","dateOfBirth":{"$date":"1985-11-22T23:00:00.000Z"},"placeOfBirth":"Messina","address":"Via Indipendenza 1","city":"Bologna","phoneNumber":"0511111111","gender":"FEMALE"},{"_id":{"$oid":"59351e15c3b3736ee0fa5f9f"},"_class":"it.euris.fullstack.model.Person","name":"Luca","surname":"Bianchi","dateOfBirth":{"$date":"1985-11-22T23:00:00.000Z"},"placeOfBirth":"Messina","address":"Via Indipendenza 1","city":"Roma","phoneNumber":"0511111111","gender":"MALE"},{"_id":{"$oid":"59351e15c3b3736ee0fa5fa0"},"_class":"it.euris.fullstack.model.Person","name":"Mario","surname":"Bianchi","dateOfBirth":{"$date":"1985-11-22T23:00:00.000Z"},"placeOfBirth":"Messina","address":"Via Indipendenza 1","city":"Bologna","phoneNumber":"0511111111","gender":"FEMALE"},{"_id":{"$oid":"59351e15c3b3736ee0fa5fa1"},"_class":"it.euris.fullstack.model.Person","name":"Mario","surname":"Bianchi","dateOfBirth":{"$date":"1985-11-22T23:00:00.000Z"},"placeOfBirth":"Messina","address":"Via Indipendenza 1","city":"Roma","phoneNumber":"0511111111","gender":"MALE"},{"_id":{"$oid":"59351e15c3b3736ee0fa5fa2"},"_class":"it.euris.fullstack.model.Person","name":"Mario","surname":"Rossi","dateOfBirth":{"$date":"1985-11-22T23:00:00.000Z"},"placeOfBirth":"Messina","address":"Via Indipendenza 1","city":"Bologna","phoneNumber":"0511111111","gender":"MALE"},{"_id":{"$oid":"59351e15c3b3736ee0fa5fa3"},"_class":"it.euris.fullstack.model.Person","name":"Mario","surname":"Rossi","dateOfBirth":{"$date":"1985-11-22T23:00:00.000Z"},"placeOfBirth":"Messina","address":"Via Indipendenza 1","city":"Roma","phoneNumber":"0511111111","gender":"MALE"},{"_id":{"$oid":"59351e15c3b3736ee0fa5fa4"},"_class":"it.euris.fullstack.model.Person","name":"Mario","surname":"Bianchi","dateOfBirth":{"$date":"1985-11-22T23:00:00.000Z"},"placeOfBirth":"Messina","address":"Via Indipendenza 1","city":"Bologna","phoneNumber":"0511111111","gender":"FEMALE"},{"_id":{"$oid":"59351e15c3b3736ee0fa5fa5"},"_class":"it.euris.fullstack.model.Person","name":"Luca","surname":"Rossi","dateOfBirth":{"$date":"1985-11-22T23:00:00.000Z"},"placeOfBirth":"Messina","address":"Via Indipendenza 1","city":"Bologna","phoneNumber":"0511111111","gender":"MALE"},{"_id":{"$oid":"59351e15c3b3736ee0fa5fa6"},"_class":"it.euris.fullstack.model.Person","name":"Mario","surname":"Bianchi","dateOfBirth":{"$date":"1985-11-22T23:00:00.000Z"},"placeOfBirth":"Messina","address":"Via Indipendenza 1","city":"Bologna","phoneNumber":"0511111111","gender":"MALE"},{"_id":{"$oid":"59351e15c3b3736ee0fa5fa7"},"_class":"it.euris.fullstack.model.Person","name":"Luca","surname":"Rossi","dateOfBirth":{"$date":"1985-11-22T23:00:00.000Z"},"placeOfBirth":"Messina","address":"Via Indipendenza 1","city":"Bologna","phoneNumber":"0511111111","gender":"FEMALE"},{"_id":{"$oid":"59351e15c3b3736ee0fa5fa8"},"_class":"it.euris.fullstack.model.Person","name":"Luca","surname":"Bianchi","dateOfBirth":{"$date":"1985-11-22T23:00:00.000Z"},"placeOfBirth":"Messina","address":"Via Indipendenza 1","city":"Bologna","phoneNumber":"0511111111","gender":"MALE"},{"_id":{"$oid":"59351e15c3b3736ee0fa5fa9"},"_class":"it.euris.fullstack.model.Person","name":"Mario","surname":"Bianchi","dateOfBirth":{"$date":"1985-11-22T23:00:00.000Z"},"placeOfBirth":"Messina","address":"Via Indipendenza 1","city":"Roma","phoneNumber":"0511111111","gender":"FEMALE"},{"_id":{"$oid":"59351e15c3b3736ee0fa5faa"},"_class":"it.euris.fullstack.model.Person","name":"Luca","surname":"Rossi","dateOfBirth":{"$date":"1985-11-22T23:00:00.000Z"},"placeOfBirth":"Messina","address":"Via Indipendenza 1","city":"Roma","phoneNumber":"0511111111","gender":"FEMALE"},{"_id":{"$oid":"59351e15c3b3736ee0fa5fab"},"_class":"it.euris.fullstack.model.Person","name":"Luca","surname":"Bianchi","dateOfBirth":{"$date":"1985-11-22T23:00:00.000Z"},"placeOfBirth":"Messina","address":"Via Indipendenza 1","city":"Bologna","phoneNumber":"0511111111","gender":"MALE"},{"_id":{"$oid":"59351e15c3b3736ee0fa5fac"},"_class":"it.euris.fullstack.model.Person","name":"Luca","surname":"Rossi","dateOfBirth":{"$date":"1985-11-22T23:00:00.000Z"},"placeOfBirth":"Messina","address":"Via Indipendenza 1","city":"Bologna","phoneNumber":"0511111111","gender":"FEMALE"},{"_id":{"$oid":"59351e15c3b3736ee0fa5fad"},"_class":"it.euris.fullstack.model.Person","name":"Luca","surname":"Bianchi","dateOfBirth":{"$date":"1985-11-22T23:00:00.000Z"},"placeOfBirth":"Messina","address":"Via Indipendenza 1","city":"Roma","phoneNumber":"0511111111","gender":"FEMALE"},{"_id":{"$oid":"59351e15c3b3736ee0fa5fae"},"_class":"it.euris.fullstack.model.Person","name":"Luca","surname":"Bianchi","dateOfBirth":{"$date":"1985-11-22T23:00:00.000Z"},"placeOfBirth":"Messina","address":"Via Indipendenza 1","city":"Roma","phoneNumber":"0511111111","gender":"FEMALE"},{"_id":{"$oid":"59351e15c3b3736ee0fa5faf"},"_class":"it.euris.fullstack.model.Person","name":"Luca","surname":"Bianchi","dateOfBirth":{"$date":"1985-11-22T23:00:00.000Z"},"placeOfBirth":"Messina","address":"Via Indipendenza 1","city":"Roma","phoneNumber":"0511111111","gender":"MALE"},{"_id":{"$oid":"59351e15c3b3736ee0fa5fb0"},"_class":"it.euris.fullstack.model.Person","name":"Luca","surname":"Rossi","dateOfBirth":{"$date":"1985-11-22T23:00:00.000Z"},"placeOfBirth":"Messina","address":"Via Indipendenza 1","city":"Bologna","phoneNumber":"0511111111","gender":"FEMALE"},{"_id":{"$oid":"59351e15c3b3736ee0fa5fb1"},"_class":"it.euris.fullstack.model.Person","name":"Mario","surname":"Bianchi","dateOfBirth":{"$date":"1985-11-22T23:00:00.000Z"},"placeOfBirth":"Messina","address":"Via Indipendenza 1","city":"Bologna","phoneNumber":"0511111111","gender":"FEMALE"},{"_id":{"$oid":"59351e15c3b3736ee0fa5fb2"},"_class":"it.euris.fullstack.model.Person","name":"Luca","surname":"Rossi","dateOfBirth":{"$date":"1985-11-22T23:00:00.000Z"},"placeOfBirth":"Messina","address":"Via Indipendenza 1","city":"Roma","phoneNumber":"0511111111","gender":"FEMALE"},{"_id":{"$oid":"59351e15c3b3736ee0fa5fb3"},"_class":"it.euris.fullstack.model.Person","name":"Luca","surname":"Bianchi","dateOfBirth":{"$date":"1985-11-22T23:00:00.000Z"},"placeOfBirth":"Messina","address":"Via Indipendenza 1","city":"Bologna","phoneNumber":"0511111111","gender":"MALE"},{"_id":{"$oid":"59351e15c3b3736ee0fa5fb4"},"_class":"it.euris.fullstack.model.Person","name":"Mario","surname":"Rossi","dateOfBirth":{"$date":"1985-11-22T23:00:00.000Z"},"placeOfBirth":"Messina","address":"Via Indipendenza 1","city":"Roma","phoneNumber":"0511111111","gender":"MALE"},{"_id":{"$oid":"59351e15c3b3736ee0fa5fb5"},"_class":"it.euris.fullstack.model.Person","name":"Luca","surname":"Bianchi","dateOfBirth":{"$date":"1985-11-22T23:00:00.000Z"},"placeOfBirth":"Messina","address":"Via Indipendenza 1","city":"Bologna","phoneNumber":"0511111111","gender":"FEMALE"},{"_id":{"$oid":"59351e15c3b3736ee0fa5fb6"},"_class":"it.euris.fullstack.model.Person","name":"Mario","surname":"Rossi","dateOfBirth":{"$date":"1985-11-22T23:00:00.000Z"},"placeOfBirth":"Messina","address":"Via Indipendenza 1","city":"Bologna","phoneNumber":"0511111111","gender":"FEMALE"},{"_id":{"$oid":"59351e15c3b3736ee0fa5fb7"},"_class":"it.euris.fullstack.model.Person","name":"Luca","surname":"Rossi","dateOfBirth":{"$date":"1985-11-22T23:00:00.000Z"},"placeOfBirth":"Messina","address":"Via Indipendenza 1","city":"Bologna","phoneNumber":"0511111111","gender":"MALE"},{"_id":{"$oid":"59351e15c3b3736ee0fa5fb8"},"_class":"it.euris.fullstack.model.Person","name":"Luca","surname":"Rossi","dateOfBirth":{"$date":"1985-11-22T23:00:00.000Z"},"placeOfBirth":"Messina","address":"Via Indipendenza 1","city":"Bologna","phoneNumber":"0511111111","gender":"FEMALE"},{"_id":{"$oid":"59351e15c3b3736ee0fa5fb9"},"_class":"it.euris.fullstack.model.Person","name":"Luca","surname":"Bianchi","dateOfBirth":{"$date":"1985-11-22T23:00:00.000Z"},"placeOfBirth":"Messina","address":"Via Indipendenza 1","city":"Bologna","phoneNumber":"0511111111","gender":"MALE"},{"_id":{"$oid":"59351e15c3b3736ee0fa5fba"},"_class":"it.euris.fullstack.model.Person","name":"Mario","surname":"Bianchi","dateOfBirth":{"$date":"1985-11-22T23:00:00.000Z"},"placeOfBirth":"Messina","address":"Via Indipendenza 1","city":"Bologna","phoneNumber":"0511111111","gender":"MALE"},{"_id":{"$oid":"59351e15c3b3736ee0fa5fbb"},"_class":"it.euris.fullstack.model.Person","name":"Mario","surname":"Rossi","dateOfBirth":{"$date":"1985-11-22T23:00:00.000Z"},"placeOfBirth":"Messina","address":"Via Indipendenza 1","city":"Bologna","phoneNumber":"0511111111","gender":"MALE"},{"_id":{"$oid":"59351e15c3b3736ee0fa5fbc"},"_class":"it.euris.fullstack.model.Person","name":"Mario","surname":"Bianchi","dateOfBirth":{"$date":"1985-11-22T23:00:00.000Z"},"placeOfBirth":"Messina","address":"Via Indipendenza 1","city":"Roma","phoneNumber":"0511111111","gender":"MALE"},{"_id":{"$oid":"59351e15c3b3736ee0fa5fbd"},"_class":"it.euris.fullstack.model.Person","name":"Mario","surname":"Rossi","dateOfBirth":{"$date":"1985-11-22T23:00:00.000Z"},"placeOfBirth":"Messina","address":"Via Indipendenza 1","city":"Roma","phoneNumber":"0511111111","gender":"FEMALE"},{"_id":{"$oid":"59351e15c3b3736ee0fa5fbe"},"_class":"it.euris.fullstack.model.Person","name":"Luca","surname":"Rossi","dateOfBirth":{"$date":"1985-11-22T23:00:00.000Z"},"placeOfBirth":"Messina","address":"Via Indipendenza 1","city":"Bologna","phoneNumber":"0511111111","gender":"MALE"},{"_id":{"$oid":"59351e15c3b3736ee0fa5fbf"},"_class":"it.euris.fullstack.model.Person","name":"Luca","surname":"Rossi","dateOfBirth":{"$date":"1985-11-22T23:00:00.000Z"},"placeOfBirth":"Messina","address":"Via Indipendenza 1","city":"Bologna","phoneNumber":"0511111111","gender":"MALE"},{"_id":{"$oid":"59351e15c3b3736ee0fa5fc0"},"_class":"it.euris.fullstack.model.Person","name":"Mario","surname":"Bianchi","dateOfBirth":{"$date":"1985-11-22T23:00:00.000Z"},"placeOfBirth":"Messina","address":"Via Indipendenza 1","city":"Roma","phoneNumber":"0511111111","gender":"FEMALE"},{"_id":{"$oid":"59351e15c3b3736ee0fa5fc1"},"_class":"it.euris.fullstack.model.Person","name":"Luca","surname":"Rossi","dateOfBirth":{"$date":"1985-11-22T23:00:00.000Z"},"placeOfBirth":"Messina","address":"Via Indipendenza 1","city":"Bologna","phoneNumber":"0511111111","gender":"FEMALE"},{"_id":{"$oid":"59351e15c3b3736ee0fa5fc2"},"_class":"it.euris.fullstack.model.Person","name":"Luca","surname":"Bianchi","dateOfBirth":{"$date":"1985-11-22T23:00:00.000Z"},"placeOfBirth":"Messina","address":"Via Indipendenza 1","city":"Roma","phoneNumber":"0511111111","gender":"MALE"},{"_id":{"$oid":"59351e15c3b3736ee0fa5fc3"},"_class":"it.euris.fullstack.model.Person","name":"Mario","surname":"Rossi","dateOfBirth":{"$date":"1985-11-22T23:00:00.000Z"},"placeOfBirth":"Messina","address":"Via Indipendenza 1","city":"Roma","phoneNumber":"0511111111","gender":"MALE"}]
